LICENSE.md
MANIFEST.in
README.md
VERSION
setup.py
django_templateyak.egg-info/PKG-INFO
django_templateyak.egg-info/SOURCES.txt
django_templateyak.egg-info/dependency_links.txt
django_templateyak.egg-info/requires.txt
django_templateyak.egg-info/top_level.txt
yak/__init__.py
yak/apps.py
yak/component.py
yak/djangles.py
yak/exceptions.py
yak/tags.py
yak/tests.py
yak/utils.py
yak/templatetags/django_yak.py
yak/templatetags/yak.py